databricks_cdk/__init__.py
databricks_cdk/cluster.py
databricks_cdk/cluster_permissions.py
databricks_cdk/credentials.py
databricks_cdk/dbfs_file.py
databricks_cdk/group.py
databricks_cdk/handler.py
databricks_cdk/instance_pools.py
databricks_cdk/instance_profile.py
databricks_cdk/job.py
databricks_cdk/networks.py
databricks_cdk/secret.py
databricks_cdk/secret_scope.py
databricks_cdk/storage_config.py
databricks_cdk/user.py
databricks_cdk/utils.py
databricks_cdk/workspace.py
databricks_cdk-0.3.5.dist-info/WHEEL
databricks_cdk-0.3.5.dist-info/METADATA
databricks_cdk-0.3.5.dist-info/RECORD
